ahserver/__init__.py
ahserver/auth_api.py
ahserver/baseProcessor.py
ahserver/configuredServer.py
ahserver/dbadmin.py
ahserver/dsProcessor.py
ahserver/error.py
ahserver/filedownload.py
ahserver/filestorage.py
ahserver/filetest.py
ahserver/functionProcessor.py
ahserver/globalEnv.py
ahserver/llmProcessor.py
ahserver/llm_client.py
ahserver/loadplugins.py
ahserver/myTE.py
ahserver/p2p_middleware.py
ahserver/processorResource.py
ahserver/proxyProcessor.py
ahserver/real_ip.py
ahserver/restful.py
ahserver/serverenv.py
ahserver/sqldsProcessor.py
ahserver/uriop.py
ahserver/url2file.py
ahserver/utils.py
ahserver/version.py
ahserver/webapp.py
ahserver/websocketProcessor.py
ahserver/xlsxData.py
ahserver/xlsxdsProcessor.py
ahserver/xtermProcessor.py
ahserver-1.1.1.dist-info/METADATA
ahserver-1.1.1.dist-info/WHEEL
ahserver-1.1.1.dist-info/top_level.txt
ahserver-1.1.1.dist-info/RECORD
