Metadata-Version: 2.4
Name: ahserver
Version: 1.1.1
Summary: A application server base on aiohttp
Author: yu moqing
Author-email: yumoqing@gmail.com
License: MIT
Requires-Python: >=3.8
Requires-Dist: redis
Requires-Dist: asyncio
Requires-Dist: aiofiles
Requires-Dist: aiodns
Requires-Dist: aiohttp==3.10.10
Requires-Dist: aiohttp_session
Requires-Dist: aiohttp_auth_autz
Requires-Dist: aiohttp-middlewares
Requires-Dist: aiohttp-cors
Requires-Dist: aiomysql
Requires-Dist: aioredis
Requires-Dist: psycopg2-binary
Requires-Dist: aiopg
Requires-Dist: jinja2
Requires-Dist: ujson
Requires-Dist: openpyxl
Requires-Dist: pillow
Requires-Dist: py-natpmp
